bitsightpy/__init__.py
bitsightpy/alerts/__init__.py
bitsightpy/alerts/calls.py
bitsightpy/base/__init__.py
bitsightpy/base/call_api.py
bitsightpy/base/call_schema.py
bitsightpy/cli.py
bitsightpy/companies/__init__.py
bitsightpy/companies/calls.py
bitsightpy/finding_details/__init__.py
bitsightpy/finding_details/calls.py
bitsightpy/folders/__init__.py
bitsightpy/folders/calls.py
bitsightpy/get_endpoints.py
bitsightpy/insights/__init__.py
bitsightpy/insights/calls.py
bitsightpy/portfolio/__init__.py
bitsightpy/portfolio/calls.py
bitsightpy/users/__init__.py
bitsightpy/users/calls.py
bitsightpy-0.1.8.dist-info/LICENSE
bitsightpy-0.1.8.dist-info/METADATA
bitsightpy-0.1.8.dist-info/WHEEL
bitsightpy-0.1.8.dist-info/entry_points.txt
bitsightpy-0.1.8.dist-info/RECORD
