Metadata-Version: 2.1
Name: bitsightpy
Version: 0.1.8
Summary: An SDK for working with BitSight Tech APIs
License: MIT
Author: 0x41424142
Author-email: jake@jakelindsay.uk
Requires-Python: >=3.11,<4.0
Classifier: License :: OSI Approved :: MIT License
Classifier: Programming Language :: Python :: 3
Classifier: Programming Language :: Python :: 3.11
Classifier: Programming Language :: Python :: 3.12
Requires-Dist: frozendict (>=2.4.4,<3.0.0)
Requires-Dist: mkdocs (>=1.6.0,<2.0.0)
Requires-Dist: mkdocs-material (>=9.5.31,<10.0.0)
Requires-Dist: requests (>=2.32.3,<3.0.0)
Project-URL: Documentation, https://bitsightpy.jakelindsay.uk
Project-URL: Homepage, https://github.com/0x41424142/bitsightpy
Project-URL: Issues, https://github.com/0x41424142/bitsightpy/issues
Project-URL: Repository, https://github.com/0x41424142/bitsightpy
